{
    "common": {
        "name": "hpcontrol",
        "version": "0.0.4",
        "news": {
            ".0.04": {
              "en": "completely revised edition",
              "de": "Vollständig überarbeitete Version"
            },
            "0.0.1": {
                "en": "initial adapter",
                "de": "Initiale Version",
                "ru": "Первоначальный адаптер",
                "pt": "Versão inicial",
                "fr": "Version initiale",
                "nl": "Eerste release"
            }
        },
        "title": "Buderus / Alpha-Innotec Heizungssteuerung",
        "desc": {
            "en": "ioBroker hpcontrol Adapter",
            "de": "ioBroker Hpcontrol Adapter",
            "ru": "ioBroker Hpcontrol драйвер как образец",
            "pt": "Modelo de adaptador para o ioBroker",
            "fr": "ioBroker adaptateur modèle",
            "nl": "ioBroker Hpcontrol Adapter"
        },
        "platform": "Javascript/Node.js",
        "mode": "daemon",
        "icon": "hpcontrol.png",
        "enabled": true,
        "extIcon": "https://raw.githubusercontent.com/jachik/iobroker.hpcontrol/master/admin/hpcontrol.png",
        "keywords": ["hpcontrol", "buderus", "alpha innotec"],
        "readme": "https://github.com/jachik/iobroker.hpcontrol/blob/master/README.md",
        "loglevel": "info",
        "type": "hardware"
    },
    "native": {
        "hpip": "192.168.1.133",
        "hpport": 8888
    },
    "objects": [

    ]
}
